{
  "version": "7",
  "dialect": "postgresql",
  "entries": [
    {
      "idx": 0,
      "version": "7",
      "when": 1731572839686,
      "tag": "0000_third_nekra",
      "breakpoints": true
    },
    {
      "idx": 1,
      "version": "7",
      "when": 1733697058204,
      "tag": "0001_heavy_xavin",
      "breakpoints": true
    },
    {
      "idx": 2,
      "version": "7",
      "when": 1738088242593,
      "tag": "0002_lethal_nighthawk",
      "breakpoints": true
    },
    {
      "idx": 3,
      "version": "7",
      "when": 1738088629832,
      "tag": "0003_hot_micromax",
      "breakpoints": true
    },
    {
      "idx": 4,
      "version": "7",
      "when": 1738089114801,
      "tag": "0004_sad_zzzax",
      "breakpoints": true
    },
    {
      "idx": 5,
      "version": "7",
      "when": 1738730330252,
      "tag": "0005_loving_veda",
      "breakpoints": true
    },
    {
      "idx": 6,
      "version": "7",
      "when": 1739900204412,
      "tag": "0006_nasty_gambit",
      "breakpoints": true
    },
    {
      "idx": 7,
      "version": "7",
      "when": 1744827145279,
      "tag": "0007_left_mathemanic",
      "breakpoints": true
    },
    {
      "idx": 8,
      "version": "7",
      "when": 1744827880504,
      "tag": "0008_curious_doctor_doom",
      "breakpoints": true
    },
    {
      "idx": 9,
      "version": "7",
      "when": 1744827972593,
      "tag": "0009_parched_madame_masque",
      "breakpoints": true
    },
    {
      "idx": 10,
      "version": "7",
      "when": 1746659501656,
      "tag": "0010_pink_ares",
      "breakpoints": true
    },
    {
      "idx": 11,
      "version": "7",
      "when": 1747329403018,
      "tag": "0011_curved_wallow",
      "breakpoints": true
    },
    {
      "idx": 12,
      "version": "7",
      "when": 1747329583644,
      "tag": "0012_mean_valkyrie",
      "breakpoints": true
    },
    {
      "idx": 13,
      "version": "7",
      "when": 1749922490915,
      "tag": "0013_modern_rhino",
      "breakpoints": true
    },
    {
      "idx": 14,
      "version": "7",
      "when": 1757460943143,
      "tag": "0014_condemned_switch",
      "breakpoints": true
    },
    {
      "idx": 15,
      "version": "7",
      "when": 1757462398645,
      "tag": "0015_classy_vision",
      "breakpoints": true
    },
    {
      "idx": 16,
      "version": "7",
      "when": 1757468157009,
      "tag": "0016_clear_iron_man",
      "breakpoints": true
    },
    {
      "idx": 17,
      "version": "7",
      "when": 1757696396716,
      "tag": "0017_romantic_scream",
      "breakpoints": true
    },
    {
      "idx": 18,
      "version": "7",
      "when": 1764639655729,
      "tag": "0018_shallow_mindworm",
      "breakpoints": true
    },
    {
      "idx": 19,
      "version": "7",
      "when": 1767986005127,
      "tag": "0019_gorgeous_cammi",
      "breakpoints": true
    },
    {
      "idx": 20,
      "version": "7",
      "when": 1768774187654,
      "tag": "0020_slimy_wasp",
      "breakpoints": true
    },
    {
      "idx": 21,
      "version": "7",
      "when": 1769637624973,
      "tag": "0021_tricky_maddog",
      "breakpoints": true
    },
    {
      "idx": 22,
      "version": "7",
      "when": 1769639014966,
      "tag": "0022_cooing_madelyne_pryor",
      "breakpoints": true
    },
    {
      "idx": 23,
      "version": "7",
      "when": 1770167251312,
      "tag": "0023_slim_gabe_jones",
      "breakpoints": true
    },
    {
      "idx": 24,
      "version": "7",
      "when": 1774042165637,
      "tag": "0024_hesitant_wong",
      "breakpoints": true
    }
  ]
}
