{
  "10501": {
    "type": "SECTION",
    "department": "MOL BIO",
    "courseNumber": "200R",
    "sectionCode": "10501",
    "sectionNum": "B",
    "sectionType": "Lab"
  },
  "13020": {
    "type": "SECTION",
    "department": "ENGR",
    "courseNumber": "54",
    "sectionCode": "13020",
    "sectionNum": "A",
    "sectionType": "Lec"
  },
  "13050": {
    "type": "SECTION",
    "department": "ENGR",
    "courseNumber": "100",
    "sectionCode": "13050",
    "sectionNum": "A",
    "sectionType": "Lab"
  },
  "13060": {
    "type": "SECTION",
    "department": "ENGR",
    "courseNumber": "100",
    "sectionCode": "13060",
    "sectionNum": "B",
    "sectionType": "Lab"
  },
  "13070": {
    "type": "SECTION",
    "department": "ENGR",
    "courseNumber": "100",
    "sectionCode": "13070",
    "sectionNum": "C",
    "sectionType": "Lab"
  },
  "13080": {
    "type": "SECTION",
    "department": "ENGR",
    "courseNumber": "100",
    "sectionCode": "13080",
    "sectionNum": "D",
    "sectionType": "Lab"
  },
  "13090": {
    "type": "SECTION",
    "department": "ENGR",
    "courseNumber": "150",
    "sectionCode": "13090",
    "sectionNum": "A",
    "sectionType": "Lec"
  },
  "13091": {
    "type": "SECTION",
    "department": "ENGR",
    "courseNumber": "150",
    "sectionCode": "13091",
    "sectionNum": "A1",
    "sectionType": "Dis"
  },
  "13170": {
    "type": "SECTION",
    "department": "ENGR",
    "courseNumber": "195",
    "sectionCode": "13170",
    "sectionNum": "B",
    "sectionType": "Lec"
  },
  "13210": {
    "type": "SECTION",
    "department": "ENGR",
    "courseNumber": "295",
    "sectionCode": "13210",
    "sectionNum": "B",
    "sectionType": "Lec"
  },
  "13260": {
    "type": "SECTION",
    "department": "ENGR",
    "courseNumber": "199",
    "sectionCode": "13260",
    "sectionNum": "A",
    "sectionType": "Res"
  },
  "13261": {
    "type": "SECTION",
    "department": "ENGR",
    "courseNumber": "199",
    "sectionCode": "13261",
    "sectionNum": "B",
    "sectionType": "Res"
  },
  "13262": {
    "type": "SECTION",
    "department": "ENGR",
    "courseNumber": "199",
    "sectionCode": "13262",
    "sectionNum": "C",
    "sectionType": "Res"
  },
  "13263": {
    "type": "SECTION",
    "department": "ENGR",
    "courseNumber": "199",
    "sectionCode": "13263",
    "sectionNum": "D",
    "sectionType": "Res"
  },
  "13264": {
    "type": "SECTION",
    "department": "ENGR",
    "courseNumber": "199",
    "sectionCode": "13264",
    "sectionNum": "E",
    "sectionType": "Res"
  },
  "13265": {
    "type": "SECTION",
    "department": "ENGR",
    "courseNumber": "199",
    "sectionCode": "13265",
    "sectionNum": "F",
    "sectionType": "Res"
  },
  "14224": {
    "type": "SECTION",
    "department": "BME",
    "courseNumber": "199",
    "sectionCode": "14224",
    "sectionNum": "T",
    "sectionType": "Res"
  },
  "14225": {
    "type": "SECTION",
    "department": "BME",
    "courseNumber": "199",
    "sectionCode": "14225",
    "sectionNum": "U",
    "sectionType": "Res"
  },
  "14500": {
    "type": "SECTION",
    "department": "BME",
    "courseNumber": "199",
    "sectionCode": "14500",
    "sectionNum": "A",
    "sectionType": "Res"
  },
  "14501": {
    "type": "SECTION",
    "department": "BME",
    "courseNumber": "199",
    "sectionCode": "14501",
    "sectionNum": "B",
    "sectionType": "Res"
  },
  "14502": {
    "type": "SECTION",
    "department": "BME",
    "courseNumber": "199",
    "sectionCode": "14502",
    "sectionNum": "C",
    "sectionType": "Res"
  },
  "14503": {
    "type": "SECTION",
    "department": "BME",
    "courseNumber": "199",
    "sectionCode": "14503",
    "sectionNum": "D",
    "sectionType": "Res"
  },
  "14504": {
    "type": "SECTION",
    "department": "BME",
    "courseNumber": "199",
    "sectionCode": "14504",
    "sectionNum": "E",
    "sectionType": "Res"
  },
  "14509": {
    "type": "SECTION",
    "department": "BME",
    "courseNumber": "199",
    "sectionCode": "14509",
    "sectionNum": "J",
    "sectionType": "Res"
  },
  "14510": {
    "type": "SECTION",
    "department": "BME",
    "courseNumber": "199",
    "sectionCode": "14510",
    "sectionNum": "K",
    "sectionType": "Res"
  },
  "14512": {
    "type": "SECTION",
    "department": "BME",
    "courseNumber": "199",
    "sectionCode": "14512",
    "sectionNum": "M",
    "sectionType": "Res"
  },
  "14950": {
    "type": "SECTION",
    "department": "CBE",
    "courseNumber": "199",
    "sectionCode": "14950",
    "sectionNum": "A",
    "sectionType": "Res"
  },
  "15010": {
    "type": "SECTION",
    "department": "CBEMS",
    "courseNumber": "155",
    "sectionCode": "15010",
    "sectionNum": "A",
    "sectionType": "Lec"
  },
  "15011": {
    "type": "SECTION",
    "department": "CBEMS",
    "courseNumber": "155",
    "sectionCode": "15011",
    "sectionNum": "A1",
    "sectionType": "Dis"
  },
  "15100": {
    "type": "SECTION",
    "department": "CBEMS",
    "courseNumber": "199",
    "sectionCode": "15100",
    "sectionNum": "A",
    "sectionType": "Res"
  },
  "15101": {
    "type": "SECTION",
    "department": "CBEMS",
    "courseNumber": "199",
    "sectionCode": "15101",
    "sectionNum": "B",
    "sectionType": "Res"
  },
  "15102": {
    "type": "SECTION",
    "department": "CBEMS",
    "courseNumber": "199",
    "sectionCode": "15102",
    "sectionNum": "C",
    "sectionType": "Res"
  },
  "15103": {
    "type": "SECTION",
    "department": "CBEMS",
    "courseNumber": "199",
    "sectionCode": "15103",
    "sectionNum": "D",
    "sectionType": "Res"
  },
  "15104": {
    "type": "SECTION",
    "department": "CBEMS",
    "courseNumber": "199",
    "sectionCode": "15104",
    "sectionNum": "E",
    "sectionType": "Res"
  },
  "15106": {
    "type": "SECTION",
    "department": "CBEMS",
    "courseNumber": "199",
    "sectionCode": "15106",
    "sectionNum": "G",
    "sectionType": "Res"
  },
  "15180": {
    "type": "SECTION",
    "department": "CBEMS",
    "courseNumber": "299",
    "sectionCode": "15180",
    "sectionNum": "A",
    "sectionType": "Res"
  },
  "17100": {
    "type": "SECTION",
    "department": "ENGRCEE",
    "courseNumber": "150",
    "sectionCode": "17100",
    "sectionNum": "A",
    "sectionType": "Lec"
  },
  "17101": {
    "type": "SECTION",
    "department": "ENGRCEE",
    "courseNumber": "150",
    "sectionCode": "17101",
    "sectionNum": "A1",
    "sectionType": "Dis"
  },
  "17200": {
    "type": "SECTION",
    "department": "ENGRCEE",
    "courseNumber": "199",
    "sectionCode": "17200",
    "sectionNum": "A",
    "sectionType": "Res"
  },
  "17201": {
    "type": "SECTION",
    "department": "ENGRCEE",
    "courseNumber": "199",
    "sectionCode": "17201",
    "sectionNum": "B",
    "sectionType": "Res"
  },
  "17202": {
    "type": "SECTION",
    "department": "ENGRCEE",
    "courseNumber": "199",
    "sectionCode": "17202",
    "sectionNum": "C",
    "sectionType": "Res"
  },
  "17203": {
    "type": "SECTION",
    "department": "ENGRCEE",
    "courseNumber": "199",
    "sectionCode": "17203",
    "sectionNum": "D",
    "sectionType": "Res"
  },
  "17204": {
    "type": "SECTION",
    "department": "ENGRCEE",
    "courseNumber": "199",
    "sectionCode": "17204",
    "sectionNum": "E",
    "sectionType": "Res"
  },
  "17205": {
    "type": "SECTION",
    "department": "ENGRCEE",
    "courseNumber": "199",
    "sectionCode": "17205",
    "sectionNum": "F",
    "sectionType": "Res"
  },
  "17250": {
    "type": "SECTION",
    "department": "ENGRCEE",
    "courseNumber": "297",
    "sectionCode": "17250",
    "sectionNum": "A",
    "sectionType": "Res"
  },
  "17251": {
    "type": "SECTION",
    "department": "ENGRCEE",
    "courseNumber": "297",
    "sectionCode": "17251",
    "sectionNum": "B",
    "sectionType": "Res"
  },
  "18250": {
    "type": "SECTION",
    "department": "EECS",
    "courseNumber": "199",
    "sectionCode": "18250",
    "sectionNum": "A",
    "sectionType": "Res"
  },
  "18251": {
    "type": "SECTION",
    "department": "EECS",
    "courseNumber": "199",
    "sectionCode": "18251",
    "sectionNum": "B",
    "sectionType": "Res"
  },
  "18252": {
    "type": "SECTION",
    "department": "EECS",
    "courseNumber": "199",
    "sectionCode": "18252",
    "sectionNum": "C",
    "sectionType": "Res"
  },
  "18253": {
    "type": "SECTION",
    "department": "EECS",
    "courseNumber": "199",
    "sectionCode": "18253",
    "sectionNum": "D",
    "sectionType": "Res"
  },
  "18254": {
    "type": "SECTION",
    "department": "EECS",
    "courseNumber": "199",
    "sectionCode": "18254",
    "sectionNum": "E",
    "sectionType": "Res"
  },
  "18255": {
    "type": "SECTION",
    "department": "EECS",
    "courseNumber": "199",
    "sectionCode": "18255",
    "sectionNum": "F",
    "sectionType": "Res"
  },
  "18256": {
    "type": "SECTION",
    "department": "EECS",
    "courseNumber": "199",
    "sectionCode": "18256",
    "sectionNum": "G",
    "sectionType": "Res"
  },
  "18257": {
    "type": "SECTION",
    "department": "EECS",
    "courseNumber": "199",
    "sectionCode": "18257",
    "sectionNum": "H",
    "sectionType": "Res"
  },
  "18258": {
    "type": "SECTION",
    "department": "EECS",
    "courseNumber": "199",
    "sectionCode": "18258",
    "sectionNum": "I",
    "sectionType": "Res"
  },
  "18259": {
    "type": "SECTION",
    "department": "EECS",
    "courseNumber": "199",
    "sectionCode": "18259",
    "sectionNum": "J",
    "sectionType": "Res"
  },
  "18260": {
    "type": "SECTION",
    "department": "EECS",
    "courseNumber": "199",
    "sectionCode": "18260",
    "sectionNum": "K",
    "sectionType": "Res"
  },
  "18261": {
    "type": "SECTION",
    "department": "EECS",
    "courseNumber": "199",
    "sectionCode": "18261",
    "sectionNum": "L",
    "sectionType": "Res"
  },
  "18262": {
    "type": "SECTION",
    "department": "EECS",
    "courseNumber": "199",
    "sectionCode": "18262",
    "sectionNum": "M",
    "sectionType": "Res"
  },
  "18263": {
    "type": "SECTION",
    "department": "EECS",
    "courseNumber": "199",
    "sectionCode": "18263",
    "sectionNum": "N",
    "sectionType": "Res"
  },
  "18329": {
    "type": "SECTION",
    "department": "EECS",
    "courseNumber": "299",
    "sectionCode": "18329",
    "sectionNum": "E",
    "sectionType": "Res"
  },
  "18330": {
    "type": "SECTION",
    "department": "EECS",
    "courseNumber": "299",
    "sectionCode": "18330",
    "sectionNum": "F",
    "sectionType": "Res"
  },
  "19030": {
    "type": "SECTION",
    "department": "ENGRMAE",
    "courseNumber": "52",
    "sectionCode": "19030",
    "sectionNum": "A",
    "sectionType": "Lec"
  },
  "19031": {
    "type": "SECTION",
    "department": "ENGRMAE",
    "courseNumber": "52",
    "sectionCode": "19031",
    "sectionNum": "A1",
    "sectionType": "Lab"
  },
  "19050": {
    "type": "SECTION",
    "department": "ENGRMAE",
    "courseNumber": "91",
    "sectionCode": "19050",
    "sectionNum": "A",
    "sectionType": "Lec"
  },
  "19100": {
    "type": "SECTION",
    "department": "ENGRMAE",
    "courseNumber": "115",
    "sectionCode": "19100",
    "sectionNum": "A",
    "sectionType": "Lec"
  },
  "19101": {
    "type": "SECTION",
    "department": "ENGRMAE",
    "courseNumber": "115",
    "sectionCode": "19101",
    "sectionNum": "A1",
    "sectionType": "Dis"
  },
  "19140": {
    "type": "SECTION",
    "department": "ENGRMAE",
    "courseNumber": "150",
    "sectionCode": "19140",
    "sectionNum": "A",
    "sectionType": "Lec"
  },
  "19141": {
    "type": "SECTION",
    "department": "ENGRMAE",
    "courseNumber": "150",
    "sectionCode": "19141",
    "sectionNum": "A1",
    "sectionType": "Dis"
  },
  "19150": {
    "type": "SECTION",
    "department": "ENGRMAE",
    "courseNumber": "150L",
    "sectionCode": "19150",
    "sectionNum": "A",
    "sectionType": "Lab"
  },
  "19160": {
    "type": "SECTION",
    "department": "ENGRMAE",
    "courseNumber": "156",
    "sectionCode": "19160",
    "sectionNum": "A",
    "sectionType": "Lec"
  },
  "19161": {
    "type": "SECTION",
    "department": "ENGRMAE",
    "courseNumber": "156",
    "sectionCode": "19161",
    "sectionNum": "A1",
    "sectionType": "Dis"
  },
  "19170": {
    "type": "SECTION",
    "department": "ENGRMAE",
    "courseNumber": "170",
    "sectionCode": "19170",
    "sectionNum": "A",
    "sectionType": "Lec"
  },
  "19171": {
    "type": "SECTION",
    "department": "ENGRMAE",
    "courseNumber": "170",
    "sectionCode": "19171",
    "sectionNum": "A1",
    "sectionType": "Dis"
  },
  "19250": {
    "type": "SECTION",
    "department": "ENGRMAE",
    "courseNumber": "199",
    "sectionCode": "19250",
    "sectionNum": "A",
    "sectionType": "Res"
  },
  "19251": {
    "type": "SECTION",
    "department": "ENGRMAE",
    "courseNumber": "199",
    "sectionCode": "19251",
    "sectionNum": "B",
    "sectionType": "Res"
  },
  "19252": {
    "type": "SECTION",
    "department": "ENGRMAE",
    "courseNumber": "199",
    "sectionCode": "19252",
    "sectionNum": "C",
    "sectionType": "Res"
  },
  "19253": {
    "type": "SECTION",
    "department": "ENGRMAE",
    "courseNumber": "199",
    "sectionCode": "19253",
    "sectionNum": "D",
    "sectionType": "Res"
  },
  "19255": {
    "type": "SECTION",
    "department": "ENGRMAE",
    "courseNumber": "199",
    "sectionCode": "19255",
    "sectionNum": "F",
    "sectionType": "Res"
  },
  "19256": {
    "type": "SECTION",
    "department": "ENGRMAE",
    "courseNumber": "199",
    "sectionCode": "19256",
    "sectionNum": "G",
    "sectionType": "Res"
  },
  "19258": {
    "type": "SECTION",
    "department": "ENGRMAE",
    "courseNumber": "199",
    "sectionCode": "19258",
    "sectionNum": "I",
    "sectionType": "Res"
  },
  "19261": {
    "type": "SECTION",
    "department": "ENGRMAE",
    "courseNumber": "199",
    "sectionCode": "19261",
    "sectionNum": "L",
    "sectionType": "Res"
  },
  "19267": {
    "type": "SECTION",
    "department": "ENGRMAE",
    "courseNumber": "199",
    "sectionCode": "19267",
    "sectionNum": "R",
    "sectionType": "Res"
  },
  "19287": {
    "type": "SECTION",
    "department": "ENGRMAE",
    "courseNumber": "297",
    "sectionCode": "19287",
    "sectionNum": "C",
    "sectionType": "Res"
  },
  "20005": {
    "type": "SECTION",
    "department": "AC ENG",
    "courseNumber": "20C",
    "sectionCode": "20005",
    "sectionNum": "A",
    "sectionType": "Lec"
  },
  "21100": {
    "type": "SECTION",
    "department": "ART HIS",
    "courseNumber": "199",
    "sectionCode": "21100",
    "sectionNum": "A",
    "sectionType": "Tut"
  },
  "24200": {
    "type": "SECTION",
    "department": "FLM&MDA",
    "courseNumber": "197",
    "sectionCode": "24200",
    "sectionNum": "A",
    "sectionType": "Fld"
  },
  "26750": {
    "type": "SECTION",
    "department": "HISTORY",
    "courseNumber": "199",
    "sectionCode": "26750",
    "sectionNum": "A",
    "sectionType": "Tut"
  },
  "33020": {
    "type": "SECTION",
    "department": "WRITING",
    "courseNumber": "31",
    "sectionCode": "33020",
    "sectionNum": "A",
    "sectionType": "Sem"
  },
  "33030": {
    "type": "SECTION",
    "department": "WRITING",
    "courseNumber": "39A",
    "sectionCode": "33030",
    "sectionNum": "A",
    "sectionType": "Sem"
  },
  "33031": {
    "type": "SECTION",
    "department": "WRITING",
    "courseNumber": "39A",
    "sectionCode": "33031",
    "sectionNum": "B",
    "sectionType": "Sem"
  },
  "33032": {
    "type": "SECTION",
    "department": "WRITING",
    "courseNumber": "39A",
    "sectionCode": "33032",
    "sectionNum": "C",
    "sectionType": "Sem"
  },
  "33033": {
    "type": "SECTION",
    "department": "WRITING",
    "courseNumber": "39A",
    "sectionCode": "33033",
    "sectionNum": "D",
    "sectionType": "Sem"
  },
  "33034": {
    "type": "SECTION",
    "department": "WRITING",
    "courseNumber": "39A",
    "sectionCode": "33034",
    "sectionNum": "E",
    "sectionType": "Sem"
  },
  "33035": {
    "type": "SECTION",
    "department": "WRITING",
    "courseNumber": "39A",
    "sectionCode": "33035",
    "sectionNum": "F",
    "sectionType": "Sem"
  },
  "33036": {
    "type": "SECTION",
    "department": "WRITING",
    "courseNumber": "39A",
    "sectionCode": "33036",
    "sectionNum": "G",
    "sectionType": "Sem"
  },
  "33037": {
    "type": "SECTION",
    "department": "WRITING",
    "courseNumber": "39A",
    "sectionCode": "33037",
    "sectionNum": "H",
    "sectionType": "Sem"
  },
  "33050": {
    "type": "SECTION",
    "department": "WRITING",
    "courseNumber": "39B",
    "sectionCode": "33050",
    "sectionNum": "A",
    "sectionType": "Sem"
  },
  "33051": {
    "type": "SECTION",
    "department": "WRITING",
    "courseNumber": "39B",
    "sectionCode": "33051",
    "sectionNum": "B",
    "sectionType": "Sem"
  },
  "33052": {
    "type": "SECTION",
    "department": "WRITING",
    "courseNumber": "39B",
    "sectionCode": "33052",
    "sectionNum": "C",
    "sectionType": "Sem"
  },
  "33053": {
    "type": "SECTION",
    "department": "WRITING",
    "courseNumber": "39B",
    "sectionCode": "33053",
    "sectionNum": "D",
    "sectionType": "Sem"
  },
  "33054": {
    "type": "SECTION",
    "department": "WRITING",
    "courseNumber": "39B",
    "sectionCode": "33054",
    "sectionNum": "E",
    "sectionType": "Sem"
  },
  "33055": {
    "type": "SECTION",
    "department": "WRITING",
    "courseNumber": "39B",
    "sectionCode": "33055",
    "sectionNum": "F",
    "sectionType": "Sem"
  },
  "33056": {
    "type": "SECTION",
    "department": "WRITING",
    "courseNumber": "39B",
    "sectionCode": "33056",
    "sectionNum": "G",
    "sectionType": "Sem"
  },
  "33057": {
    "type": "SECTION",
    "department": "WRITING",
    "courseNumber": "39B",
    "sectionCode": "33057",
    "sectionNum": "H",
    "sectionType": "Sem"
  },
  "33058": {
    "type": "SECTION",
    "department": "WRITING",
    "courseNumber": "39B",
    "sectionCode": "33058",
    "sectionNum": "I",
    "sectionType": "Sem"
  },
  "33059": {
    "type": "SECTION",
    "department": "WRITING",
    "courseNumber": "39B",
    "sectionCode": "33059",
    "sectionNum": "J",
    "sectionType": "Sem"
  },
  "33060": {
    "type": "SECTION",
    "department": "WRITING",
    "courseNumber": "39B",
    "sectionCode": "33060",
    "sectionNum": "K",
    "sectionType": "Sem"
  },
  "33061": {
    "type": "SECTION",
    "department": "WRITING",
    "courseNumber": "39B",
    "sectionCode": "33061",
    "sectionNum": "L",
    "sectionType": "Sem"
  },
  "33080": {
    "type": "SECTION",
    "department": "WRITING",
    "courseNumber": "39C",
    "sectionCode": "33080",
    "sectionNum": "A",
    "sectionType": "Sem"
  },
  "33081": {
    "type": "SECTION",
    "department": "WRITING",
    "courseNumber": "39C",
    "sectionCode": "33081",
    "sectionNum": "B",
    "sectionType": "Sem"
  },
  "33082": {
    "type": "SECTION",
    "department": "WRITING",
    "courseNumber": "39C",
    "sectionCode": "33082",
    "sectionNum": "C",
    "sectionType": "Sem"
  },
  "33083": {
    "type": "SECTION",
    "department": "WRITING",
    "courseNumber": "39C",
    "sectionCode": "33083",
    "sectionNum": "D",
    "sectionType": "Sem"
  },
  "33084": {
    "type": "SECTION",
    "department": "WRITING",
    "courseNumber": "39C",
    "sectionCode": "33084",
    "sectionNum": "E",
    "sectionType": "Sem"
  },
  "33085": {
    "type": "SECTION",
    "department": "WRITING",
    "courseNumber": "39C",
    "sectionCode": "33085",
    "sectionNum": "F",
    "sectionType": "Sem"
  },
  "33086": {
    "type": "SECTION",
    "department": "WRITING",
    "courseNumber": "39C",
    "sectionCode": "33086",
    "sectionNum": "G",
    "sectionType": "Sem"
  },
  "33087": {
    "type": "SECTION",
    "department": "WRITING",
    "courseNumber": "39C",
    "sectionCode": "33087",
    "sectionNum": "H",
    "sectionType": "Sem"
  },
  "33088": {
    "type": "SECTION",
    "department": "WRITING",
    "courseNumber": "39C",
    "sectionCode": "33088",
    "sectionNum": "I",
    "sectionType": "Sem"
  },
  "33089": {
    "type": "SECTION",
    "department": "WRITING",
    "courseNumber": "39C",
    "sectionCode": "33089",
    "sectionNum": "J",
    "sectionType": "Sem"
  },
  "33090": {
    "type": "SECTION",
    "department": "WRITING",
    "courseNumber": "39C",
    "sectionCode": "33090",
    "sectionNum": "K",
    "sectionType": "Sem"
  },
  "33091": {
    "type": "SECTION",
    "department": "WRITING",
    "courseNumber": "39C",
    "sectionCode": "33091",
    "sectionNum": "L",
    "sectionType": "Sem"
  },
  "33092": {
    "type": "SECTION",
    "department": "WRITING",
    "courseNumber": "39C",
    "sectionCode": "33092",
    "sectionNum": "M",
    "sectionType": "Sem"
  },
  "33093": {
    "type": "SECTION",
    "department": "WRITING",
    "courseNumber": "39C",
    "sectionCode": "33093",
    "sectionNum": "N",
    "sectionType": "Sem"
  },
  "33094": {
    "type": "SECTION",
    "department": "WRITING",
    "courseNumber": "39C",
    "sectionCode": "33094",
    "sectionNum": "O",
    "sectionType": "Sem"
  },
  "33095": {
    "type": "SECTION",
    "department": "WRITING",
    "courseNumber": "39C",
    "sectionCode": "33095",
    "sectionNum": "P",
    "sectionType": "Sem"
  },
  "33096": {
    "type": "SECTION",
    "department": "WRITING",
    "courseNumber": "39C",
    "sectionCode": "33096",
    "sectionNum": "Q",
    "sectionType": "Sem"
  },
  "33097": {
    "type": "SECTION",
    "department": "WRITING",
    "courseNumber": "39C",
    "sectionCode": "33097",
    "sectionNum": "R",
    "sectionType": "Sem"
  },
  "33098": {
    "type": "SECTION",
    "department": "WRITING",
    "courseNumber": "39C",
    "sectionCode": "33098",
    "sectionNum": "S",
    "sectionType": "Sem"
  },
  "33099": {
    "type": "SECTION",
    "department": "WRITING",
    "courseNumber": "39C",
    "sectionCode": "33099",
    "sectionNum": "T",
    "sectionType": "Sem"
  },
  "33100": {
    "type": "SECTION",
    "department": "WRITING",
    "courseNumber": "39C",
    "sectionCode": "33100",
    "sectionNum": "U",
    "sectionType": "Sem"
  },
  "33101": {
    "type": "SECTION",
    "department": "WRITING",
    "courseNumber": "39C",
    "sectionCode": "33101",
    "sectionNum": "V",
    "sectionType": "Sem"
  },
  "33102": {
    "type": "SECTION",
    "department": "WRITING",
    "courseNumber": "39C",
    "sectionCode": "33102",
    "sectionNum": "W",
    "sectionType": "Sem"
  },
  "33103": {
    "type": "SECTION",
    "department": "WRITING",
    "courseNumber": "39C",
    "sectionCode": "33103",
    "sectionNum": "X",
    "sectionType": "Sem"
  },
  "33104": {
    "type": "SECTION",
    "department": "WRITING",
    "courseNumber": "39C",
    "sectionCode": "33104",
    "sectionNum": "Y",
    "sectionType": "Sem"
  },
  "33105": {
    "type": "SECTION",
    "department": "WRITING",
    "courseNumber": "39C",
    "sectionCode": "33105",
    "sectionNum": "Z",
    "sectionType": "Sem"
  },
  "33106": {
    "type": "SECTION",
    "department": "WRITING",
    "courseNumber": "39C",
    "sectionCode": "33106",
    "sectionNum": "AA",
    "sectionType": "Sem"
  },
  "33107": {
    "type": "SECTION",
    "department": "WRITING",
    "courseNumber": "39C",
    "sectionCode": "33107",
    "sectionNum": "AB",
    "sectionType": "Sem"
  },
  "33108": {
    "type": "SECTION",
    "department": "WRITING",
    "courseNumber": "39C",
    "sectionCode": "33108",
    "sectionNum": "AC",
    "sectionType": "Sem"
  },
  "33109": {
    "type": "SECTION",
    "department": "WRITING",
    "courseNumber": "39C",
    "sectionCode": "33109",
    "sectionNum": "AD",
    "sectionType": "Sem"
  },
  "33110": {
    "type": "SECTION",
    "department": "WRITING",
    "courseNumber": "39C",
    "sectionCode": "33110",
    "sectionNum": "AE",
    "sectionType": "Sem"
  },
  "33111": {
    "type": "SECTION",
    "department": "WRITING",
    "courseNumber": "39C",
    "sectionCode": "33111",
    "sectionNum": "AF",
    "sectionType": "Sem"
  },
  "33112": {
    "type": "SECTION",
    "department": "WRITING",
    "courseNumber": "39C",
    "sectionCode": "33112",
    "sectionNum": "AG",
    "sectionType": "Sem"
  },
  "33113": {
    "type": "SECTION",
    "department": "WRITING",
    "courseNumber": "39C",
    "sectionCode": "33113",
    "sectionNum": "AH",
    "sectionType": "Sem"
  },
  "33114": {
    "type": "SECTION",
    "department": "WRITING",
    "courseNumber": "39C",
    "sectionCode": "33114",
    "sectionNum": "AI",
    "sectionType": "Sem"
  },
  "33115": {
    "type": "SECTION",
    "department": "WRITING",
    "courseNumber": "39C",
    "sectionCode": "33115",
    "sectionNum": "AJ",
    "sectionType": "Sem"
  },
  "33116": {
    "type": "SECTION",
    "department": "WRITING",
    "courseNumber": "39C",
    "sectionCode": "33116",
    "sectionNum": "AK",
    "sectionType": "Sem"
  },
  "33117": {
    "type": "SECTION",
    "department": "WRITING",
    "courseNumber": "39C",
    "sectionCode": "33117",
    "sectionNum": "AL",
    "sectionType": "Sem"
  },
  "33118": {
    "type": "SECTION",
    "department": "WRITING",
    "courseNumber": "39C",
    "sectionCode": "33118",
    "sectionNum": "AM",
    "sectionType": "Sem"
  },
  "33119": {
    "type": "SECTION",
    "department": "WRITING",
    "courseNumber": "39C",
    "sectionCode": "33119",
    "sectionNum": "AN",
    "sectionType": "Sem"
  },
  "33120": {
    "type": "SECTION",
    "department": "WRITING",
    "courseNumber": "39C",
    "sectionCode": "33120",
    "sectionNum": "AO",
    "sectionType": "Sem"
  },
  "33121": {
    "type": "SECTION",
    "department": "WRITING",
    "courseNumber": "39C",
    "sectionCode": "33121",
    "sectionNum": "AP",
    "sectionType": "Sem"
  },
  "33122": {
    "type": "SECTION",
    "department": "WRITING",
    "courseNumber": "39C",
    "sectionCode": "33122",
    "sectionNum": "AQ",
    "sectionType": "Sem"
  },
  "33123": {
    "type": "SECTION",
    "department": "WRITING",
    "courseNumber": "39C",
    "sectionCode": "33123",
    "sectionNum": "AR",
    "sectionType": "Sem"
  },
  "33124": {
    "type": "SECTION",
    "department": "WRITING",
    "courseNumber": "39C",
    "sectionCode": "33124",
    "sectionNum": "AS",
    "sectionType": "Sem"
  },
  "33125": {
    "type": "SECTION",
    "department": "WRITING",
    "courseNumber": "39C",
    "sectionCode": "33125",
    "sectionNum": "AT",
    "sectionType": "Sem"
  },
  "33130": {
    "type": "SECTION",
    "department": "WRITING",
    "courseNumber": "139W",
    "sectionCode": "33130",
    "sectionNum": "A",
    "sectionType": "Sem"
  },
  "33131": {
    "type": "SECTION",
    "department": "WRITING",
    "courseNumber": "139W",
    "sectionCode": "33131",
    "sectionNum": "B",
    "sectionType": "Sem"
  },
  "33132": {
    "type": "SECTION",
    "department": "WRITING",
    "courseNumber": "139W",
    "sectionCode": "33132",
    "sectionNum": "C",
    "sectionType": "Sem"
  },
  "33133": {
    "type": "SECTION",
    "department": "WRITING",
    "courseNumber": "139W",
    "sectionCode": "33133",
    "sectionNum": "D",
    "sectionType": "Sem"
  },
  "33134": {
    "type": "SECTION",
    "department": "WRITING",
    "courseNumber": "139W",
    "sectionCode": "33134",
    "sectionNum": "E",
    "sectionType": "Sem"
  },
  "33135": {
    "type": "SECTION",
    "department": "WRITING",
    "courseNumber": "139W",
    "sectionCode": "33135",
    "sectionNum": "F",
    "sectionType": "Sem"
  },
  "33136": {
    "type": "SECTION",
    "department": "WRITING",
    "courseNumber": "139W",
    "sectionCode": "33136",
    "sectionNum": "G",
    "sectionType": "Sem"
  },
  "33137": {
    "type": "SECTION",
    "department": "WRITING",
    "courseNumber": "139W",
    "sectionCode": "33137",
    "sectionNum": "H",
    "sectionType": "Sem"
  },
  "33138": {
    "type": "SECTION",
    "department": "WRITING",
    "courseNumber": "139W",
    "sectionCode": "33138",
    "sectionNum": "I",
    "sectionType": "Sem"
  },
  "34160": {
    "type": "SECTION",
    "department": "COMPSCI",
    "courseNumber": "161",
    "sectionCode": "34160",
    "sectionNum": "A",
    "sectionType": "Lec"
  },
  "34161": {
    "type": "SECTION",
    "department": "COMPSCI",
    "courseNumber": "161",
    "sectionCode": "34161",
    "sectionNum": "A1",
    "sectionType": "Dis"
  },
  "34340": {
    "type": "SECTION",
    "department": "COMPSCI",
    "courseNumber": "299P",
    "sectionCode": "34340",
    "sectionNum": "C",
    "sectionType": "Tut"
  },
  "34701": {
    "type": "SECTION",
    "department": "COMPSCI",
    "courseNumber": "199",
    "sectionCode": "34701",
    "sectionNum": "B",
    "sectionType": "Tut"
  },
  "34702": {
    "type": "SECTION",
    "department": "COMPSCI",
    "courseNumber": "199",
    "sectionCode": "34702",
    "sectionNum": "C",
    "sectionType": "Tut"
  },
  "34703": {
    "type": "SECTION",
    "department": "COMPSCI",
    "courseNumber": "199",
    "sectionCode": "34703",
    "sectionNum": "D",
    "sectionType": "Tut"
  },
  "34704": {
    "type": "SECTION",
    "department": "COMPSCI",
    "courseNumber": "199",
    "sectionCode": "34704",
    "sectionNum": "E",
    "sectionType": "Tut"
  },
  "34705": {
    "type": "SECTION",
    "department": "COMPSCI",
    "courseNumber": "199",
    "sectionCode": "34705",
    "sectionNum": "F",
    "sectionType": "Tut"
  },
  "34706": {
    "type": "SECTION",
    "department": "COMPSCI",
    "courseNumber": "199",
    "sectionCode": "34706",
    "sectionNum": "G",
    "sectionType": "Tut"
  },
  "34707": {
    "type": "SECTION",
    "department": "COMPSCI",
    "courseNumber": "199",
    "sectionCode": "34707",
    "sectionNum": "H",
    "sectionType": "Tut"
  },
  "34708": {
    "type": "SECTION",
    "department": "COMPSCI",
    "courseNumber": "199",
    "sectionCode": "34708",
    "sectionNum": "I",
    "sectionType": "Tut"
  },
  "34709": {
    "type": "SECTION",
    "department": "COMPSCI",
    "courseNumber": "199",
    "sectionCode": "34709",
    "sectionNum": "J",
    "sectionType": "Tut"
  },
  "34710": {
    "type": "SECTION",
    "department": "COMPSCI",
    "courseNumber": "199",
    "sectionCode": "34710",
    "sectionNum": "K",
    "sectionType": "Tut"
  },
  "34711": {
    "type": "SECTION",
    "department": "COMPSCI",
    "courseNumber": "199",
    "sectionCode": "34711",
    "sectionNum": "L",
    "sectionType": "Tut"
  },
  "34712": {
    "type": "SECTION",
    "department": "COMPSCI",
    "courseNumber": "199",
    "sectionCode": "34712",
    "sectionNum": "M",
    "sectionType": "Tut"
  },
  "34713": {
    "type": "SECTION",
    "department": "COMPSCI",
    "courseNumber": "199",
    "sectionCode": "34713",
    "sectionNum": "N",
    "sectionType": "Tut"
  },
  "34714": {
    "type": "SECTION",
    "department": "COMPSCI",
    "courseNumber": "199",
    "sectionCode": "34714",
    "sectionNum": "O",
    "sectionType": "Tut"
  },
  "34717": {
    "type": "SECTION",
    "department": "COMPSCI",
    "courseNumber": "199",
    "sectionCode": "34717",
    "sectionNum": "R",
    "sectionType": "Tut"
  },
  "34720": {
    "type": "SECTION",
    "department": "COMPSCI",
    "courseNumber": "199",
    "sectionCode": "34720",
    "sectionNum": "U",
    "sectionType": "Tut"
  },
  "34721": {
    "type": "SECTION",
    "department": "COMPSCI",
    "courseNumber": "199",
    "sectionCode": "34721",
    "sectionNum": "V",
    "sectionType": "Tut"
  },
  "34722": {
    "type": "SECTION",
    "department": "COMPSCI",
    "courseNumber": "199",
    "sectionCode": "34722",
    "sectionNum": "W",
    "sectionType": "Tut"
  },
  "34723": {
    "type": "SECTION",
    "department": "COMPSCI",
    "courseNumber": "199",
    "sectionCode": "34723",
    "sectionNum": "X",
    "sectionType": "Tut"
  },
  "34728": {
    "type": "SECTION",
    "department": "COMPSCI",
    "courseNumber": "199",
    "sectionCode": "34728",
    "sectionNum": "AC",
    "sectionType": "Tut"
  },
  "34729": {
    "type": "SECTION",
    "department": "COMPSCI",
    "courseNumber": "199",
    "sectionCode": "34729",
    "sectionNum": "AD",
    "sectionType": "Tut"
  },
  "34732": {
    "type": "SECTION",
    "department": "COMPSCI",
    "courseNumber": "199",
    "sectionCode": "34732",
    "sectionNum": "AG",
    "sectionType": "Tut"
  },
  "34912": {
    "type": "SECTION",
    "department": "COMPSCI",
    "courseNumber": "299",
    "sectionCode": "34912",
    "sectionNum": "M",
    "sectionType": "Tut"
  },
  "34941": {
    "type": "SECTION",
    "department": "COMPSCI",
    "courseNumber": "299",
    "sectionCode": "34941",
    "sectionNum": "AP",
    "sectionType": "Tut"
  },
  "34944": {
    "type": "SECTION",
    "department": "COMPSCI",
    "courseNumber": "299",
    "sectionCode": "34944",
    "sectionNum": "AS",
    "sectionType": "Tut"
  },
  "34958": {
    "type": "SECTION",
    "department": "COMPSCI",
    "courseNumber": "299",
    "sectionCode": "34958",
    "sectionNum": "BG",
    "sectionType": "Tut"
  },
  "34961": {
    "type": "SECTION",
    "department": "COMPSCI",
    "courseNumber": "299",
    "sectionCode": "34961",
    "sectionNum": "BJ",
    "sectionType": "Tut"
  },
  "34962": {
    "type": "SECTION",
    "department": "COMPSCI",
    "courseNumber": "299",
    "sectionCode": "34962",
    "sectionNum": "BK",
    "sectionType": "Tut"
  },
  "36540": {
    "type": "SECTION",
    "department": "I&C SCI",
    "courseNumber": "31",
    "sectionCode": "36540",
    "sectionNum": "A",
    "sectionType": "Lec"
  },
  "36541": {
    "type": "SECTION",
    "department": "I&C SCI",
    "courseNumber": "31",
    "sectionCode": "36541",
    "sectionNum": "A1",
    "sectionType": "Lab"
  },
  "36542": {
    "type": "SECTION",
    "department": "I&C SCI",
    "courseNumber": "31",
    "sectionCode": "36542",
    "sectionNum": "A2",
    "sectionType": "Lab"
  },
  "36550": {
    "type": "SECTION",
    "department": "I&C SCI",
    "courseNumber": "32",
    "sectionCode": "36550",
    "sectionNum": "A",
    "sectionType": "Lec"
  },
  "36551": {
    "type": "SECTION",
    "department": "I&C SCI",
    "courseNumber": "32",
    "sectionCode": "36551",
    "sectionNum": "A1",
    "sectionType": "Lab"
  },
  "36555": {
    "type": "SECTION",
    "department": "I&C SCI",
    "courseNumber": "32",
    "sectionCode": "36555",
    "sectionNum": "B",
    "sectionType": "Lec"
  },
  "36556": {
    "type": "SECTION",
    "department": "I&C SCI",
    "courseNumber": "32",
    "sectionCode": "36556",
    "sectionNum": "B1",
    "sectionType": "Lab"
  },
  "36560": {
    "type": "SECTION",
    "department": "I&C SCI",
    "courseNumber": "33",
    "sectionCode": "36560",
    "sectionNum": "A",
    "sectionType": "Lec"
  },
  "36561": {
    "type": "SECTION",
    "department": "I&C SCI",
    "courseNumber": "33",
    "sectionCode": "36561",
    "sectionNum": "A1",
    "sectionType": "Lab"
  },
  "36562": {
    "type": "SECTION",
    "department": "I&C SCI",
    "courseNumber": "33",
    "sectionCode": "36562",
    "sectionNum": "A2",
    "sectionType": "Lab"
  },
  "36570": {
    "type": "SECTION",
    "department": "I&C SCI",
    "courseNumber": "45C",
    "sectionCode": "36570",
    "sectionNum": "A",
    "sectionType": "Lec"
  },
  "36700": {
    "type": "SECTION",
    "department": "I&C SCI",
    "courseNumber": "192",
    "sectionCode": "36700",
    "sectionNum": "A",
    "sectionType": "Fld"
  },
  "37060": {
    "type": "SECTION",
    "department": "IN4MATX",
    "courseNumber": "131",
    "sectionCode": "37060",
    "sectionNum": "A",
    "sectionType": "Lec"
  },
  "37100": {
    "type": "SECTION",
    "department": "IN4MATX",
    "courseNumber": "286",
    "sectionCode": "37100",
    "sectionNum": "A",
    "sectionType": "Lec"
  },
  "37110": {
    "type": "SECTION",
    "department": "IN4MATX",
    "courseNumber": "288",
    "sectionCode": "37110",
    "sectionNum": "A",
    "sectionType": "Lec"
  },
  "37530": {
    "type": "SECTION",
    "department": "IN4MATX",
    "courseNumber": "199",
    "sectionCode": "37530",
    "sectionNum": "A",
    "sectionType": "Tut"
  },
  "37531": {
    "type": "SECTION",
    "department": "IN4MATX",
    "courseNumber": "199",
    "sectionCode": "37531",
    "sectionNum": "B",
    "sectionType": "Tut"
  },
  "37532": {
    "type": "SECTION",
    "department": "IN4MATX",
    "courseNumber": "199",
    "sectionCode": "37532",
    "sectionNum": "C",
    "sectionType": "Tut"
  },
  "37560": {
    "type": "SECTION",
    "department": "IN4MATX",
    "courseNumber": "299",
    "sectionCode": "37560",
    "sectionNum": "K",
    "sectionType": "Tut"
  },
  "37563": {
    "type": "SECTION",
    "department": "IN4MATX",
    "courseNumber": "299",
    "sectionCode": "37563",
    "sectionNum": "N",
    "sectionType": "Tut"
  },
  "37574": {
    "type": "SECTION",
    "department": "IN4MATX",
    "courseNumber": "299",
    "sectionCode": "37574",
    "sectionNum": "Y",
    "sectionType": "Tut"
  },
  "37575": {
    "type": "SECTION",
    "department": "IN4MATX",
    "courseNumber": "299",
    "sectionCode": "37575",
    "sectionNum": "Z",
    "sectionType": "Tut"
  },
  "37940": {
    "type": "SECTION",
    "department": "STATS",
    "courseNumber": "199",
    "sectionCode": "37940",
    "sectionNum": "A",
    "sectionType": "Res"
  },
  "38693": {
    "type": "SECTION",
    "department": "MGMTMBA",
    "courseNumber": "290",
    "sectionCode": "38693",
    "sectionNum": "A",
    "sectionType": "Sem"
  },
  "38694": {
    "type": "SECTION",
    "department": "MGMTMBA",
    "courseNumber": "290",
    "sectionCode": "38694",
    "sectionNum": "B",
    "sectionType": "Sem"
  },
  "38800": {
    "type": "SECTION",
    "department": "MGMTPHD",
    "courseNumber": "299",
    "sectionCode": "38800",
    "sectionNum": "A",
    "sectionType": "Tut"
  },
  "38803": {
    "type": "SECTION",
    "department": "MGMTPHD",
    "courseNumber": "299",
    "sectionCode": "38803",
    "sectionNum": "D",
    "sectionType": "Tut"
  },
  "39912": {
    "type": "SECTION",
    "department": "FIN",
    "courseNumber": "211",
    "sectionCode": "39912",
    "sectionNum": "A",
    "sectionType": "Sem"
  },
  "39948": {
    "type": "SECTION",
    "department": "FIN",
    "courseNumber": "250",
    "sectionCode": "39948",
    "sectionNum": "A",
    "sectionType": "Lec"
  },
  "39964": {
    "type": "SECTION",
    "department": "FIN",
    "courseNumber": "290",
    "sectionCode": "39964",
    "sectionNum": "A",
    "sectionType": "Lec"
  },
  "39981": {
    "type": "SECTION",
    "department": "FIN",
    "courseNumber": "299",
    "sectionCode": "39981",
    "sectionNum": "A",
    "sectionType": "Res"
  },
  "39982": {
    "type": "SECTION",
    "department": "FIN",
    "courseNumber": "299",
    "sectionCode": "39982",
    "sectionNum": "C",
    "sectionType": "Res"
  },
  "39984": {
    "type": "SECTION",
    "department": "FIN",
    "courseNumber": "299",
    "sectionCode": "39984",
    "sectionNum": "B",
    "sectionType": "Res"
  },
  "39985": {
    "type": "SECTION",
    "department": "FIN",
    "courseNumber": "296",
    "sectionCode": "39985",
    "sectionNum": "A",
    "sectionType": "Sem"
  },
  "39986": {
    "type": "SECTION",
    "department": "FIN",
    "courseNumber": "299",
    "sectionCode": "39986",
    "sectionNum": "1",
    "sectionType": "Res"
  },
  "39988": {
    "type": "SECTION",
    "department": "FIN",
    "courseNumber": "255",
    "sectionCode": "39988",
    "sectionNum": "INT",
    "sectionType": "Lec"
  },
  "40652": {
    "type": "SECTION",
    "department": "CHEM",
    "courseNumber": "180",
    "sectionCode": "40652",
    "sectionNum": "C",
    "sectionType": "Res"
  },
  "40653": {
    "type": "SECTION",
    "department": "CHEM",
    "courseNumber": "180",
    "sectionCode": "40653",
    "sectionNum": "D",
    "sectionType": "Res"
  },
  "40654": {
    "type": "SECTION",
    "department": "CHEM",
    "courseNumber": "180",
    "sectionCode": "40654",
    "sectionNum": "E",
    "sectionType": "Res"
  },
  "40675": {
    "type": "SECTION",
    "department": "CHEM",
    "courseNumber": "199",
    "sectionCode": "40675",
    "sectionNum": "A",
    "sectionType": "Tut"
  },
  "40676": {
    "type": "SECTION",
    "department": "CHEM",
    "courseNumber": "199",
    "sectionCode": "40676",
    "sectionNum": "B",
    "sectionType": "Tut"
  },
  "40677": {
    "type": "SECTION",
    "department": "CHEM",
    "courseNumber": "199",
    "sectionCode": "40677",
    "sectionNum": "C",
    "sectionType": "Tut"
  },
  "40750": {
    "type": "SECTION",
    "department": "CHEM",
    "courseNumber": "299",
    "sectionCode": "40750",
    "sectionNum": "A",
    "sectionType": "Tut"
  },
  "40751": {
    "type": "SECTION",
    "department": "CHEM",
    "courseNumber": "299",
    "sectionCode": "40751",
    "sectionNum": "B",
    "sectionType": "Tut"
  },
  "40753": {
    "type": "SECTION",
    "department": "CHEM",
    "courseNumber": "299",
    "sectionCode": "40753",
    "sectionNum": "D",
    "sectionType": "Tut"
  },
  "42090": {
    "type": "SECTION",
    "department": "EARTHSS",
    "courseNumber": "198W",
    "sectionCode": "42090",
    "sectionNum": "A",
    "sectionType": "Lec"
  },
  "42100": {
    "type": "SECTION",
    "department": "EARTHSS",
    "courseNumber": "199",
    "sectionCode": "42100",
    "sectionNum": "A",
    "sectionType": "Res"
  },
  "42101": {
    "type": "SECTION",
    "department": "EARTHSS",
    "courseNumber": "199",
    "sectionCode": "42101",
    "sectionNum": "B",
    "sectionType": "Res"
  },
  "42130": {
    "type": "SECTION",
    "department": "EARTHSS",
    "courseNumber": "299",
    "sectionCode": "42130",
    "sectionNum": "A",
    "sectionType": "Res"
  },
  "44801": {
    "type": "SECTION",
    "department": "MATH",
    "courseNumber": "199A",
    "sectionCode": "44801",
    "sectionNum": "B",
    "sectionType": "Res"
  },
  "47040": {
    "type": "SECTION",
    "department": "PHYSICS",
    "courseNumber": "3LB",
    "sectionCode": "47040",
    "sectionNum": "A1",
    "sectionType": "Lab"
  },
  "47041": {
    "type": "SECTION",
    "department": "PHYSICS",
    "courseNumber": "3LB",
    "sectionCode": "47041",
    "sectionNum": "A2",
    "sectionType": "Lab"
  },
  "47042": {
    "type": "SECTION",
    "department": "PHYSICS",
    "courseNumber": "3LB",
    "sectionCode": "47042",
    "sectionNum": "A3",
    "sectionType": "Lab"
  },
  "47043": {
    "type": "SECTION",
    "department": "PHYSICS",
    "courseNumber": "3LB",
    "sectionCode": "47043",
    "sectionNum": "A4",
    "sectionType": "Lab"
  },
  "47044": {
    "type": "SECTION",
    "department": "PHYSICS",
    "courseNumber": "3LB",
    "sectionCode": "47044",
    "sectionNum": "A5",
    "sectionType": "Lab"
  },
  "47045": {
    "type": "SECTION",
    "department": "PHYSICS",
    "courseNumber": "3LB",
    "sectionCode": "47045",
    "sectionNum": "A6",
    "sectionType": "Lab"
  },
  "47060": {
    "type": "SECTION",
    "department": "PHYSICS",
    "courseNumber": "3LC",
    "sectionCode": "47060",
    "sectionNum": "A1",
    "sectionType": "Lab"
  },
  "47061": {
    "type": "SECTION",
    "department": "PHYSICS",
    "courseNumber": "3LC",
    "sectionCode": "47061",
    "sectionNum": "A2",
    "sectionType": "Lab"
  },
  "47062": {
    "type": "SECTION",
    "department": "PHYSICS",
    "courseNumber": "3LC",
    "sectionCode": "47062",
    "sectionNum": "A3",
    "sectionType": "Lab"
  },
  "47063": {
    "type": "SECTION",
    "department": "PHYSICS",
    "courseNumber": "3LC",
    "sectionCode": "47063",
    "sectionNum": "A4",
    "sectionType": "Lab"
  },
  "47064": {
    "type": "SECTION",
    "department": "PHYSICS",
    "courseNumber": "3LC",
    "sectionCode": "47064",
    "sectionNum": "A5",
    "sectionType": "Lab"
  },
  "47065": {
    "type": "SECTION",
    "department": "PHYSICS",
    "courseNumber": "3LC",
    "sectionCode": "47065",
    "sectionNum": "A6",
    "sectionType": "Lab"
  },
  "47250": {
    "type": "SECTION",
    "department": "PHYSICS",
    "courseNumber": "295",
    "sectionCode": "47250",
    "sectionNum": "A",
    "sectionType": "Res"
  },
  "50100": {
    "type": "SECTION",
    "department": "SOCECOL",
    "courseNumber": "195",
    "sectionCode": "50100",
    "sectionNum": "C",
    "sectionType": "Fld"
  },
  "50110": {
    "type": "SECTION",
    "department": "SOCECOL",
    "courseNumber": "195",
    "sectionCode": "50110",
    "sectionNum": "D",
    "sectionType": "Fld"
  },
  "55212": {
    "type": "SECTION",
    "department": "UPPP",
    "courseNumber": "299",
    "sectionCode": "55212",
    "sectionNum": "C",
    "sectionType": "Tut"
  },
  "55213": {
    "type": "SECTION",
    "department": "UPPP",
    "courseNumber": "299",
    "sectionCode": "55213",
    "sectionNum": "D",
    "sectionType": "Tut"
  },
  "60901": {
    "type": "SECTION",
    "department": "ANTHRO",
    "courseNumber": "199",
    "sectionCode": "60901",
    "sectionNum": "B",
    "sectionType": "Tut"
  },
  "60902": {
    "type": "SECTION",
    "department": "ANTHRO",
    "courseNumber": "199",
    "sectionCode": "60902",
    "sectionNum": "C",
    "sectionType": "Tut"
  },
  "60960": {
    "type": "SECTION",
    "department": "ANTHRO",
    "courseNumber": "299",
    "sectionCode": "60960",
    "sectionNum": "A",
    "sectionType": "Tut"
  },
  "60961": {
    "type": "SECTION",
    "department": "ANTHRO",
    "courseNumber": "299",
    "sectionCode": "60961",
    "sectionNum": "B",
    "sectionType": "Tut"
  },
  "61200": {
    "type": "SECTION",
    "department": "CHC/LAT",
    "courseNumber": "199",
    "sectionCode": "61200",
    "sectionNum": "A",
    "sectionType": "Tut"
  },
  "61201": {
    "type": "SECTION",
    "department": "CHC/LAT",
    "courseNumber": "199",
    "sectionCode": "61201",
    "sectionNum": "B",
    "sectionType": "Tut"
  },
  "62903": {
    "type": "SECTION",
    "department": "ECON",
    "courseNumber": "199",
    "sectionCode": "62903",
    "sectionNum": "D",
    "sectionType": "Tut"
  },
  "62950": {
    "type": "SECTION",
    "department": "ECON",
    "courseNumber": "290",
    "sectionCode": "62950",
    "sectionNum": "A",
    "sectionType": "Res"
  },
  "65950": {
    "type": "SECTION",
    "department": "LINGUIS",
    "courseNumber": "299",
    "sectionCode": "65950",
    "sectionNum": "A",
    "sectionType": "Tut"
  },
  "67970": {
    "type": "SECTION",
    "department": "POL SCI",
    "courseNumber": "299",
    "sectionCode": "67970",
    "sectionNum": "A",
    "sectionType": "Tut"
  },
  "68950": {
    "type": "SECTION",
    "department": "PSYCH",
    "courseNumber": "299",
    "sectionCode": "68950",
    "sectionNum": "A",
    "sectionType": "Tut"
  },
  "69960": {
    "type": "SECTION",
    "department": "SOCIOL",
    "courseNumber": "299",
    "sectionCode": "69960",
    "sectionNum": "A",
    "sectionType": "Tut"
  },
  "88010": {
    "type": "SECTION",
    "department": "NUR SCI",
    "courseNumber": "262",
    "sectionCode": "88010",
    "sectionNum": "A",
    "sectionType": "Lab"
  },
  "88895": {
    "type": "SECTION",
    "department": "PHRMSCI",
    "courseNumber": "197",
    "sectionCode": "88895",
    "sectionNum": "A",
    "sectionType": "Fld"
  },
  "88900": {
    "type": "SECTION",
    "department": "PHRMSCI",
    "courseNumber": "198",
    "sectionCode": "88900",
    "sectionNum": "A",
    "sectionType": "Res"
  },
  "89200": {
    "type": "SECTION",
    "department": "PUBHLTH",
    "courseNumber": "195W",
    "sectionCode": "89200",
    "sectionNum": "A",
    "sectionType": "Lec"
  },
  "89201": {
    "type": "SECTION",
    "department": "PUBHLTH",
    "courseNumber": "195W",
    "sectionCode": "89201",
    "sectionNum": "A1",
    "sectionType": "Dis"
  },
  "89202": {
    "type": "SECTION",
    "department": "PUBHLTH",
    "courseNumber": "195W",
    "sectionCode": "89202",
    "sectionNum": "A2",
    "sectionType": "Dis"
  },
  "89203": {
    "type": "SECTION",
    "department": "PUBHLTH",
    "courseNumber": "195W",
    "sectionCode": "89203",
    "sectionNum": "A3",
    "sectionType": "Dis"
  },
  "89300": {
    "type": "SECTION",
    "department": "PUBHLTH",
    "courseNumber": "295",
    "sectionCode": "89300",
    "sectionNum": "A",
    "sectionType": "Fld"
  },
  "89452": {
    "type": "SECTION",
    "department": "PUBHLTH",
    "courseNumber": "199",
    "sectionCode": "89452",
    "sectionNum": "C",
    "sectionType": "Res"
  },
  "90450": {
    "type": "SECTION",
    "department": "BATS",
    "courseNumber": "296",
    "sectionCode": "90450",
    "sectionNum": "A",
    "sectionType": "Sem"
  },
  "06051": {
    "type": "SECTION",
    "department": "BIO SCI",
    "courseNumber": "199",
    "sectionCode": "06051",
    "sectionNum": "B",
    "sectionType": "Res"
  },
  "06055": {
    "type": "SECTION",
    "department": "BIO SCI",
    "courseNumber": "199",
    "sectionCode": "06055",
    "sectionNum": "F",
    "sectionType": "Res"
  },
  "06056": {
    "type": "SECTION",
    "department": "BIO SCI",
    "courseNumber": "199",
    "sectionCode": "06056",
    "sectionNum": "G",
    "sectionType": "Res"
  },
  "06234": {
    "type": "SECTION",
    "department": "BIO SCI",
    "courseNumber": "199",
    "sectionCode": "06234",
    "sectionNum": "CI",
    "sectionType": "Res"
  },
  "06200": {
    "type": "SECTION",
    "department": "BIO SCI",
    "courseNumber": "199",
    "sectionCode": "06200",
    "sectionNum": "BA",
    "sectionType": "Res"
  },
  "06207": {
    "type": "SECTION",
    "department": "BIO SCI",
    "courseNumber": "199",
    "sectionCode": "06207",
    "sectionNum": "BH",
    "sectionType": "Res"
  },
  "06318": {
    "type": "SECTION",
    "department": "BIO SCI",
    "courseNumber": "199",
    "sectionCode": "06318",
    "sectionNum": "FS",
    "sectionType": "Res"
  },
  "06531": {
    "type": "SECTION",
    "department": "BIO SCI",
    "courseNumber": "199",
    "sectionCode": "06531",
    "sectionNum": "OF",
    "sectionType": "Res"
  },
  "06211": {
    "type": "SECTION",
    "department": "BIO SCI",
    "courseNumber": "199",
    "sectionCode": "06211",
    "sectionNum": "BL",
    "sectionType": "Res"
  },
  "06466": {
    "type": "SECTION",
    "department": "BIO SCI",
    "courseNumber": "199",
    "sectionCode": "06466",
    "sectionNum": "KO",
    "sectionType": "Res"
  },
  "06224": {
    "type": "SECTION",
    "department": "BIO SCI",
    "courseNumber": "199",
    "sectionCode": "06224",
    "sectionNum": "BY",
    "sectionType": "Res"
  },
  "06231": {
    "type": "SECTION",
    "department": "BIO SCI",
    "courseNumber": "199",
    "sectionCode": "06231",
    "sectionNum": "CF",
    "sectionType": "Res"
  },
  "06235": {
    "type": "SECTION",
    "department": "BIO SCI",
    "courseNumber": "199",
    "sectionCode": "06235",
    "sectionNum": "CJ",
    "sectionType": "Res"
  },
  "06240": {
    "type": "SECTION",
    "department": "BIO SCI",
    "courseNumber": "199",
    "sectionCode": "06240",
    "sectionNum": "CO",
    "sectionType": "Res"
  },
  "06300": {
    "type": "SECTION",
    "department": "BIO SCI",
    "courseNumber": "199",
    "sectionCode": "06300",
    "sectionNum": "FA",
    "sectionType": "Res"
  },
  "06442": {
    "type": "SECTION",
    "department": "BIO SCI",
    "courseNumber": "199",
    "sectionCode": "06442",
    "sectionNum": "JQ",
    "sectionType": "Res"
  },
  "06302": {
    "type": "SECTION",
    "department": "BIO SCI",
    "courseNumber": "199",
    "sectionCode": "06302",
    "sectionNum": "FC",
    "sectionType": "Res"
  },
  "06331": {
    "type": "SECTION",
    "department": "BIO SCI",
    "courseNumber": "199",
    "sectionCode": "06331",
    "sectionNum": "GF",
    "sectionType": "Res"
  },
  "06308": {
    "type": "SECTION",
    "department": "BIO SCI",
    "courseNumber": "199",
    "sectionCode": "06308",
    "sectionNum": "FI",
    "sectionType": "Res"
  },
  "06312": {
    "type": "SECTION",
    "department": "BIO SCI",
    "courseNumber": "199",
    "sectionCode": "06312",
    "sectionNum": "FM",
    "sectionType": "Res"
  },
  "06315": {
    "type": "SECTION",
    "department": "BIO SCI",
    "courseNumber": "199",
    "sectionCode": "06315",
    "sectionNum": "FP",
    "sectionType": "Res"
  },
  "06507": {
    "type": "SECTION",
    "department": "BIO SCI",
    "courseNumber": "199",
    "sectionCode": "06507",
    "sectionNum": "NH",
    "sectionType": "Res"
  },
  "06316": {
    "type": "SECTION",
    "department": "BIO SCI",
    "courseNumber": "199",
    "sectionCode": "06316",
    "sectionNum": "FQ",
    "sectionType": "Res"
  },
  "06326": {
    "type": "SECTION",
    "department": "BIO SCI",
    "courseNumber": "199",
    "sectionCode": "06326",
    "sectionNum": "GA",
    "sectionType": "Res"
  },
  "06333": {
    "type": "SECTION",
    "department": "BIO SCI",
    "courseNumber": "199",
    "sectionCode": "06333",
    "sectionNum": "GH",
    "sectionType": "Res"
  },
  "06401": {
    "type": "SECTION",
    "department": "BIO SCI",
    "courseNumber": "199",
    "sectionCode": "06401",
    "sectionNum": "IB",
    "sectionType": "Res"
  },
  "06407": {
    "type": "SECTION",
    "department": "BIO SCI",
    "courseNumber": "199",
    "sectionCode": "06407",
    "sectionNum": "IH",
    "sectionType": "Res"
  },
  "06416": {
    "type": "SECTION",
    "department": "BIO SCI",
    "courseNumber": "199",
    "sectionCode": "06416",
    "sectionNum": "IQ",
    "sectionType": "Res"
  },
  "06516": {
    "type": "SECTION",
    "department": "BIO SCI",
    "courseNumber": "199",
    "sectionCode": "06516",
    "sectionNum": "NQ",
    "sectionType": "Res"
  },
  "06419": {
    "type": "SECTION",
    "department": "BIO SCI",
    "courseNumber": "199",
    "sectionCode": "06419",
    "sectionNum": "IT",
    "sectionType": "Res"
  },
  "06420": {
    "type": "SECTION",
    "department": "BIO SCI",
    "courseNumber": "199",
    "sectionCode": "06420",
    "sectionNum": "IU",
    "sectionType": "Res"
  },
  "06425": {
    "type": "SECTION",
    "department": "BIO SCI",
    "courseNumber": "199",
    "sectionCode": "06425",
    "sectionNum": "IZ",
    "sectionType": "Res"
  },
  "06437": {
    "type": "SECTION",
    "department": "BIO SCI",
    "courseNumber": "199",
    "sectionCode": "06437",
    "sectionNum": "JL",
    "sectionType": "Res"
  },
  "06447": {
    "type": "SECTION",
    "department": "BIO SCI",
    "courseNumber": "199",
    "sectionCode": "06447",
    "sectionNum": "JV",
    "sectionType": "Res"
  },
  "06450": {
    "type": "SECTION",
    "department": "BIO SCI",
    "courseNumber": "199",
    "sectionCode": "06450",
    "sectionNum": "JY",
    "sectionType": "Res"
  },
  "06453": {
    "type": "SECTION",
    "department": "BIO SCI",
    "courseNumber": "199",
    "sectionCode": "06453",
    "sectionNum": "KB",
    "sectionType": "Res"
  },
  "06456": {
    "type": "SECTION",
    "department": "BIO SCI",
    "courseNumber": "199",
    "sectionCode": "06456",
    "sectionNum": "KE",
    "sectionType": "Res"
  },
  "06457": {
    "type": "SECTION",
    "department": "BIO SCI",
    "courseNumber": "199",
    "sectionCode": "06457",
    "sectionNum": "KF",
    "sectionType": "Res"
  },
  "06460": {
    "type": "SECTION",
    "department": "BIO SCI",
    "courseNumber": "199",
    "sectionCode": "06460",
    "sectionNum": "KI",
    "sectionType": "Res"
  },
  "06463": {
    "type": "SECTION",
    "department": "BIO SCI",
    "courseNumber": "199",
    "sectionCode": "06463",
    "sectionNum": "KL",
    "sectionType": "Res"
  },
  "06471": {
    "type": "SECTION",
    "department": "BIO SCI",
    "courseNumber": "199",
    "sectionCode": "06471",
    "sectionNum": "KT",
    "sectionType": "Res"
  },
  "06472": {
    "type": "SECTION",
    "department": "BIO SCI",
    "courseNumber": "199",
    "sectionCode": "06472",
    "sectionNum": "KU",
    "sectionType": "Res"
  },
  "06474": {
    "type": "SECTION",
    "department": "BIO SCI",
    "courseNumber": "199",
    "sectionCode": "06474",
    "sectionNum": "KW",
    "sectionType": "Res"
  },
  "06493": {
    "type": "SECTION",
    "department": "BIO SCI",
    "courseNumber": "199",
    "sectionCode": "06493",
    "sectionNum": "LP",
    "sectionType": "Res"
  },
  "06494": {
    "type": "SECTION",
    "department": "BIO SCI",
    "courseNumber": "199",
    "sectionCode": "06494",
    "sectionNum": "LQ",
    "sectionType": "Res"
  },
  "06520": {
    "type": "SECTION",
    "department": "BIO SCI",
    "courseNumber": "199",
    "sectionCode": "06520",
    "sectionNum": "NU",
    "sectionType": "Res"
  },
  "06499": {
    "type": "SECTION",
    "department": "BIO SCI",
    "courseNumber": "199",
    "sectionCode": "06499",
    "sectionNum": "LV",
    "sectionType": "Res"
  },
  "06519": {
    "type": "SECTION",
    "department": "BIO SCI",
    "courseNumber": "199",
    "sectionCode": "06519",
    "sectionNum": "NT",
    "sectionType": "Res"
  },
  "06527": {
    "type": "SECTION",
    "department": "BIO SCI",
    "courseNumber": "199",
    "sectionCode": "06527",
    "sectionNum": "OB",
    "sectionType": "Res"
  },
  "06530": {
    "type": "SECTION",
    "department": "BIO SCI",
    "courseNumber": "199",
    "sectionCode": "06530",
    "sectionNum": "OE",
    "sectionType": "Res"
  },
  "06532": {
    "type": "SECTION",
    "department": "BIO SCI",
    "courseNumber": "199",
    "sectionCode": "06532",
    "sectionNum": "OG",
    "sectionType": "Res"
  },
  "06541": {
    "type": "SECTION",
    "department": "BIO SCI",
    "courseNumber": "199",
    "sectionCode": "06541",
    "sectionNum": "OP",
    "sectionType": "Res"
  },
  "06533": {
    "type": "SECTION",
    "department": "BIO SCI",
    "courseNumber": "199",
    "sectionCode": "06533",
    "sectionNum": "OH",
    "sectionType": "Res"
  },
  "06705": {
    "type": "SECTION",
    "department": "BIO SCI",
    "courseNumber": "199",
    "sectionCode": "06705",
    "sectionNum": "MB",
    "sectionType": "Res"
  },
  "06534": {
    "type": "SECTION",
    "department": "BIO SCI",
    "courseNumber": "199",
    "sectionCode": "06534",
    "sectionNum": "OI",
    "sectionType": "Res"
  },
  "06543": {
    "type": "SECTION",
    "department": "BIO SCI",
    "courseNumber": "199",
    "sectionCode": "06543",
    "sectionNum": "OR",
    "sectionType": "Res"
  },
  "06548": {
    "type": "SECTION",
    "department": "BIO SCI",
    "courseNumber": "199",
    "sectionCode": "06548",
    "sectionNum": "OW",
    "sectionType": "Res"
  },
  "06567": {
    "type": "SECTION",
    "department": "BIO SCI",
    "courseNumber": "199",
    "sectionCode": "06567",
    "sectionNum": "PP",
    "sectionType": "Res"
  },
  "06568": {
    "type": "SECTION",
    "department": "BIO SCI",
    "courseNumber": "199",
    "sectionCode": "06568",
    "sectionNum": "PQ",
    "sectionType": "Res"
  },
  "06706": {
    "type": "SECTION",
    "department": "BIO SCI",
    "courseNumber": "199",
    "sectionCode": "06706",
    "sectionNum": "MC",
    "sectionType": "Res"
  },
  "06707": {
    "type": "SECTION",
    "department": "BIO SCI",
    "courseNumber": "199",
    "sectionCode": "06707",
    "sectionNum": "MD",
    "sectionType": "Res"
  },
  "06708": {
    "type": "SECTION",
    "department": "BIO SCI",
    "courseNumber": "199",
    "sectionCode": "06708",
    "sectionNum": "ME",
    "sectionType": "Res"
  },
  "06710": {
    "type": "SECTION",
    "department": "BIO SCI",
    "courseNumber": "199",
    "sectionCode": "06710",
    "sectionNum": "MG",
    "sectionType": "Res"
  },
  "06713": {
    "type": "SECTION",
    "department": "BIO SCI",
    "courseNumber": "199",
    "sectionCode": "06713",
    "sectionNum": "MJ",
    "sectionType": "Res"
  },
  "06046": {
    "type": "SECTION",
    "department": "BIO SCI",
    "courseNumber": "198",
    "sectionCode": "06046",
    "sectionNum": "Q",
    "sectionType": "Res"
  },
  "09500": {
    "type": "SECTION",
    "department": "ECO EVO",
    "courseNumber": "200A",
    "sectionCode": "09500",
    "sectionNum": "A",
    "sectionType": "Res"
  },
  "01710": {
    "type": "SECTION",
    "department": "ART",
    "courseNumber": "199",
    "sectionCode": "01710",
    "sectionNum": "A",
    "sectionType": "Stu"
  },
  "03915": {
    "type": "SECTION",
    "department": "DRAMA",
    "courseNumber": "199",
    "sectionCode": "03915",
    "sectionNum": "A",
    "sectionType": "Stu"
  },
  "03917": {
    "type": "SECTION",
    "department": "DRAMA",
    "courseNumber": "199",
    "sectionCode": "03917",
    "sectionNum": "C",
    "sectionType": "Stu"
  },
  "04901": {
    "type": "SECTION",
    "department": "MUSIC",
    "courseNumber": "191",
    "sectionCode": "04901",
    "sectionNum": "B",
    "sectionType": "Tut"
  }
}